{
  "metadata": {
    "version": "4.5.0",
    "language": "Telugu",
    "script": "Telugu",
    "languageCode": "te",
    "title": "KG-Telugu v4.5: Advanced Neuro-Symbolic Knowledge Graph for Telugu",
    "description": "A revolutionary reasoning-powered knowledge graph with formal logic representation, cross-lingual alignment, neural-symbolic integration, and advanced inference capabilities for next-generation AI systems.",
    "sources": [
      "Andhra Bharati Vyākaranam",
      "Telugu Vākya Nirmiti - Dr. Bh. Krishnamurti",
      "Comparative Dravidian Linguistics - S. N. Sridhar",
      "ISO 15919:2009 Transliteration Standard",
      "Wiktionary",
      "Telugu Academy Resources",
      "AI4Bharat Indic NLP",
      "Sarvam AI Telugu Corpus",
      "FrameNet",
      "VerbNet",
      "AMR (Abstract Meaning Representation)",
      "ConceptNet",
      "WordNet"
    ],
    "license": "CC-BY-SA 4.0",
    "createdAt": "2023-10-27",
    "lastUpdated": "2025-08-28",
    "coverage": [
      "Phonology", "Orthography", "Morphology", "Syntax", "Semantics",
      "Pragmatics", "Morpho-phonemics", "Derivation", "Transliteration",
      "Ontology", "Reasoning", "TinyAI", "Domain Knowledge",
      "Neural-Symbolic Integration", "Formal Logic", "Cross-lingual Alignment",
      "Cognitive Modeling", "Multi-modal Reasoning"
    ],
    "status": "advanced-production",
    "schemaVersion": "KG-Telugu-v4.5"
  },
  "graph": {
    "namespaces": {
      "node": "https://kg.te/telugu/nodes/",
      "edge": "https://kg.te/telugu/edges/",
      "prop": "https://kg.te/telugu/properties/",
      "logic": "https://kg.te/telugu/logic/",
      "neural": "https://kg.te/telugu/neural/"
    },
    "schema": {
      "nodeTypes": [
        "Phoneme", "Grapheme", "PhonologicalRule", "MorphophonemicRule",
        "Morpheme", "Lexeme", "Paradigm", "SyntacticRule", "Construction",
        "GrammaticalRelation", "SemanticConcept", "SemanticRole", "PragmaticMarker",
        "TransliterationMap", "OrthographyRule", "UDMapping", "Template",
        "InferenceRule", "Ontology", "Domain", "LogicModule", "TinyAIProfile",
        "NeuralModule", "Frame", "Script", "CognitivePattern", "CrossLingualMap",
        "FormalRule", "Constraint", "MultiModalAnchor"
      ],
      "edgeTypes": [
        "isA", "partOf", "combinesWith", "appliesTo", "requiresModifier",
        "takesCase", "conjugatesWith", "assignsRole", "hasForm", "allomorphOf",
        "usesCaseMarker", "hasExampleComponent", "canRealize", "mapsTo",
        "derivesFrom", "licenses", "flags", "synonymOf", "antonymOf",
        "hypernymOf", "hyponymOf", "triggers", "implies", "validates", "optimizedFor",
        "entails", "contradicts", "presupposes", "neurallyLinked", "formallyEquivalent",
        "crossLingualMatch", "activates", "inhibits", "multimodalGrounds"
      ]
    },

    "nodes": [
      {
        "id": "phonology_inventory",
        "type": "Paradigm",
        "subtype": "PhonemeInventory",
        "name": "Core Telugu Phoneme Set",
        "features": {
          "syllableStructures": ["CV", "CVC", "CVV", "CCV", "CCCVC"],
          "prosody": ["declarative_fall", "yesno_rise", "wh_question_drop"],
          "sandhiRules": ["vowel_harmony", "consonant_assimilation", "elision"]
        }
      },

      // === ENHANCED PHONOLOGY WITH FORMAL RULES ===
      {"id": "vowel_a", "type": "Phoneme", "subtype": "Vowel", "teluguSymbol": "అ", "romanization": "a", "ipa": "/a/", "name": "అకారం", "properties": {"height": "low", "backness": "central", "rounding": "unrounded", "length": "short", "position": "primary", "stressable": true, "sonority": 5}},
      {"id": "vowel_aa", "type": "Phoneme", "subtype": "Vowel", "teluguSymbol": "ఆ", "romanization": "ā", "ipa": "/aː/", "name": "ఆకారం", "properties": {"height": "low", "backness": "central", "rounding": "unrounded", "length": "long", "position": "primary", "sonority": 5}},
      // ... [all vowels & consonants with enhanced features] ...
      {"id": "consonant_lla", "type": "Phoneme", "subtype": "Consonant", "teluguSymbol": "ళ", "romanization": "ḷa", "ipa": "[ɭ]", "properties": {"manner": "retroflex lateral", "voicing": "voiced", "sonority": 3}},

      // === FORMAL MORPHO-PHONEMIC RULES ===
      {
        "id": "rule_gunintam_k_i", 
        "type": "MorphophonemicRule", 
        "name": "క + ి → కి", 
        "formalRule": "C[cons, +velar] + V[+high, -back] → CV[syllabic] / _#", 
        "implementation": "finite_state_transducer",
        "example": "క + ి = కి", 
        "romanizedExample": "ka + i = ki"
      },
      {
        "id": "rule_anusvara_assimilation", 
        "type": "MorphophonemicRule", 
        "name": "Anusvara place assimilation", 
        "formalRule": "ṃ → N[αplace] / _ C[αplace]", 
        "description": "Anusvara becomes homorganic nasal before consonants.",
        "examples": ["ంప → [mp]", "ంగ → [ŋg]"]
      },
      {
        "id": "rule_retroflexion", 
        "type": "MorphophonemicRule", 
        "name": "n → ṇ / _ {ṭ, ḍ, ṇ}", 
        "formalRule": "n[+coronal, -distributed] → ṇ[+coronal, +distributed] / _ {ṭ, ḍ, ṇ}[+coronal, +distributed]",
        "description": "Dental n becomes retroflex before retroflexes across morpheme boundary."
      },

      // === ADVANCED ORTHOGRAPHY ===
      {
        "id": "orth_rule_virama", 
        "type": "OrthographyRule", 
        "name": "Virama suppresses inherent vowel", 
        "pattern": "C + ◌్ → C̚", 
        "formalization": "vowel_deletion_rule",
        "description": "Suppresses /a/ after consonant base for conjuncts.",
        "exceptions": ["loanwords", "sanskrit_origin"]
      },

      // === CROSS-LINGUAL ALIGNMENT ===
      {
        "id": "crosslingual_dravidian", 
        "type": "CrossLingualMap", 
        "name": "Dravidian Language Family Alignment",
        "languages": ["Tamil", "Kannada", "Malayalam", "Telugu"],
        "mappings": [
          {"telugu": "ఉండు", "tamil": "இரு", "kannada": "ಇರು", "malayalam": "ഉണ്ടായിരിക്കുക", "meaning": "to be"},
          {"telugu": "తిను", "tamil": "தின்", "kannada": "ತಿನ್ನು", "malayalam": "തിന്നുക", "meaning": "to eat"}
        ],
        "regularCorrespondences": [
          {"telugu": "ప", "tamil": "ப", "kannada": "ಹ", "malayalam": "പ", "environment": "word_initial"}
        ]
      },

      // === FORMAL SEMANTIC FRAMES ===
      {
        "id": "frame_ingestion", 
        "type": "Frame", 
        "name": "Ingestion", 
        "frameElements": [
          {"id": "fe_ingestor", "type": "Agent", "semanticRestrictions": ["+animate", "+volitional"]},
          {"id": "fe_ingestible", "type": "Patient", "semanticRestrictions": ["+edible", "+physical"]},
          {"id": "fe_instrument", "type": "Instrument", "optional": true, "semanticRestrictions": ["+utensil"]},
          {"id": "fe_location", "type": "Location", "optional": true}
        ],
        "lexicalUnits": ["తిను", "నములు", "పీల్చు", "మింగు"]
      },

      // === ENHANCED LEXICON WITH FORMAL FEATURES ===
      {
        "id": "noun_pilli", 
        "type": "Lexeme", 
        "subtype": "Noun", 
        "lemma": "పిల్లి", 
        "romanization": "pilli", 
        "meaning": [{"gloss": "cat", "domain": "animal", "frame": "animate_being"}], 
        "properties": {
          "gender": "feminine", 
          "animacy": "animate",
          "countability": "countable",
          "semanticFeatures": ["+animate", "+carnivore", "+domestic", "-human"]
        }, 
        "inflections": {
          "plural": "పిల్లులు", 
          "accusative": "పిల్లిని", 
          "genitive": "పిల్లి యొక్క",
          "dative": "పిల్లికి",
          "locative": "పిల్లిలో"
        },
        "neuralEmbedding": "vector_embedding_v1",
        "conceptNetUri": "/c/te/పిల్లి"
      },
      {
        "id": "verb_tinu", 
        "type": "Lexeme", 
        "subtype": "Verb", 
        "lemma": "తిను", 
        "romanization": "tinu", 
        "meaning": [{
          "gloss": "to eat", 
          "transitivity": "transitive",
          "frame": "ingestion",
          "aktionsart": "activity"
        }], 
        "root": "తిన్", 
        "stem": "తిన్", 
        "class": "class-1", 
        "voice": "active",
        "subcategorization": {
          "required": ["subject", "object"],
          "optional": ["instrument", "location"]
        },
        "selectionalRestrictions": {
          "subject": ["+animate", "+volitional"],
          "object": ["+edible", "+physical"]
        },
        "neuralEmbedding": "vector_embedding_v2"
      },

      // === FORMAL SYNTAX ===
      {
        "id": "syntax_sov", 
        "type": "SyntacticRule", 
        "name": "SOV Word Order", 
        "description": "Default SOV order; postpositions and case markers crucial.", 
        "formalRule": "S → NP[nom] (NP[acc/dat])* VP",
        "structure": "NP + NP + VP", 
        "example": "పిల్లి ఎలుకని తింటుంది", 
        "romanizedExample": "Pilli elukani tin-tundi", 
        "gloss": "cat mouse-acc eat-3sg",
        "statisticalFrequency": 0.78
      },
      {
        "id": "syntax_relative_clause", 
        "type": "SyntacticRule", 
        "name": "Relative Clause", 
        "description": "Participial relative clauses using -న/-ని.", 
        "formalRule": "NP → (Det) N (RC)",
        "example": "చదివిన పుస్తకం",
        "gloss": "read-PST.REL book",
        "headFinal": true
      },

      // === FORMAL SEMANTICS ===
      {
        "id": "semantic_animal", 
        "type": "SemanticConcept", 
        "name": "Animal", 
        "uri": "http://dbpedia.org/ontology/Animal", 
        "formalDefinition": "∀x.Animal(x) → LivingBeing(x) ∧ ¬Plant(x) ∧ ¬Human(x) ∧ CanMove(x)",
        "hypernyms": ["LivingBeing"], 
        "hyponyms": ["Feline", "Canine", "Bird"],
        "properties": ["+animate", "+mobile", "-human", "-plant"],
        "neuralEmbedding": "concept_vector_123"
      },
      {
        "id": "theta_agent", 
        "type": "SemanticRole", 
        "role": "Agent", 
        "description": "Intentional doer of action",
        "formalDefinition": "Agent(e,x) → Volitional(x) ∧ Causes(x,e)",
        "syntacticRealization": ["subject[nom]"],
        "selectionalRestrictions": ["+animate", "+volitional"]
      },

      // === FORMAL PRAGMATICS ===
      {
        "id": "prag_polite_imp", 
        "type": "PragmaticMarker", 
        "marker": "-ండి", 
        "function": "polite imperative", 
        "example": "కూర్చోండి",
        "register": "formal",
        "socialContext": ["respect", "deference", "public_setting"],
        "formalityLevel": 8
      },
      {
        "id": "prag_particle_kada", 
        "type": "PragmaticMarker", 
        "marker": "కదా/గదా", 
        "function": "assertive tag", 
        "example": "ఇది మంచిదే కదా?",
        "discourseFunction": "confirmation_seeking",
        "expectedResponse": "agreement",
        "certaintyLevel": 0.8
      },

      // === FORMAL ONTOLOGIES WITH LOGIC ===
      {
        "id": "ontology_agriculture",
        "type": "Ontology",
        "domain": "agriculture",
        "formalization": "description_logic",
        "concepts": [
          {"id": "పంట", "type": "Crop", "definition": "Plant cultivated for food"},
          {"id": "నీరు", "type": "Water", "definition": "H₂O, essential for life"},
          {"id": "రైతు", "type": "Farmer", "definition": "Person engaged in agriculture"}
        ],
        "relations": [
          {"id": "పండిస్తుంది", "type": "cultivates", "domain": "Farmer", "range": "Crop"},
          {"id": "అవసరం", "type": "requires", "domain": "Crop", "range": "Water"}
        ],
        "axioms": [
          "Farmer ⊑ ∃cultivates.Crop",
          "Crop ⊑ ∃requires.Water",
          "cultivates ◦ requires ⊑ requires"  // If farmer cultivates crop and crop requires water, then farmer requires water
        ]
      },

      // === ADVANCED INFERENCE RULES ===
      {
        "id": "rule_eat_implies_animal",
        "type": "InferenceRule",
        "name": "Eating implies animal",
        "formalLogic": "∀x,y. eat(x,y) → animate(x) ∧ edible(y)",
        "probability": 0.95,
        "exceptions": ["robots", "mythical_beings"],
        "implementation": "probabilistic_horn_clause",
        "neuralComponent": "transformer_attention"
      },
      {
        "id": "rule_causal_chain_hunger",
        "type": "InferenceRule",
        "name": "Hunger causes eating behavior",
        "formalLogic": "∀x. hungry(x) → ∃y. seek_food(x,y) ∧ (find_food(x,y) → eat(x,y))",
        "temporalAspect": "before",
        "causalStrength": 0.88
      },

      // === NEURAL-SYMBOLIC INTEGRATION ===
      {
        "id": "neural_module_bert",
        "type": "NeuralModule",
        "name": "Telugu BERT Embedder",
        "architecture": "Transformer",
        "parameters": "110M",
        "input": "telugu_text",
        "output": "contextual_embeddings",
        "trainingData": "Telugu Wikipedia, news corpora, literature",
        "integrationPoints": ["lexical_disambiguation", "context_sensitivity", "pragmatic_inference"]
      },
      {
        "id": "symbolic_reasoner",
        "type": "LogicModule",
        "name": "Telugu Reasoning Engine",
        "functions": ["semantic_inference", "pragmatic_context", "causal_logic"],
        "formalSystem": "description_logic + probabilistic_rules",
        "inputFormats": ["text", "speech", "logical_form"],
        "outputFormats": ["response", "explanation", "proof_tree"]
      },

      // === COGNITIVE MODELING ===
      {
        "id": "cognitive_script_dining",
        "type": "Script",
        "name": "Dining Script",
        "description": "Common sequence of events for eating",
        "steps": [
          {"action": "feel_hunger", "actor": "protagonist"},
          {"action": "decide_to_eat", "actor": "protagonist"},
          {"action": "obtain_food", "actor": "protagonist"},
          {"action": "consume_food", "actor": "protagonist"},
          {"action": "feel_satiated", "actor": "protagonist"}
        ],
        "culturalVariations": {
          "indian": ["serve_on_leaf", "eat_with_hands"],
          "western": ["use_utensils", "eat_at_table"]
        }
      },

      // === MULTI-MODAL GROUNDING ===
      {
        "id": "multimodal_cat",
        "type": "MultiModalAnchor",
        "concept": "పిల్లి",
        "visualRepresentations": ["image_of_cat", "video_of_cat", "drawing_of_cat"],
        "auditoryRepresentations": ["meow_sound", "purring_sound"],
        "hapticRepresentations": ["fur_texture", "cat_shape"],
        "crossModalAlignment": {
          "visual-auditory": 0.92,
          "visual-textual": 0.88,
          "auditory-textual": 0.85
        }
      },

      // === TINY AI MODULES (ENHANCED) ===
      {
        "id": "tinyai_profile_100mb",
        "type": "TinyAIProfile",
        "name": "On-Device Telugu Assistant",
        "size": "100MB",
        "capabilities": ["voice_input", "grammar_check", "verb_conjugation", "dialogue", "limited_reasoning"],
        "architecture": "neural_symbolic_fusion",
        "neuralComponents": ["lightweight_bert", "small_lstm"],
        "symbolicComponents": ["rule_engine", "ontology_reasoner"],
        "optimizations": ["knowledge_distillation", "rule_compression", "lookup_tables"]
      }
    ],

    "edges": [
      // === BASIC LINGUISTIC EDGES ===
      {"from": "consonant_ka", "to": "matra_i", "relationship": "combinesWith", "result": "కి", "rule": "rule_gunintam_k_i"},
      {"from": "rule_gunintam_k_i", "to": "consonant_ka", "relationship": "appliesTo"},
      {"from": "rule_gunintam_k_i", "to": "matra_i", "relationship": "requiresModifier"},

      {"from": "noun_pilli", "to": "case_acc", "relationship": "takesCase", "form": "పిల్లిని", "role": "object"},
      {"from": "noun_pilli", "to": "semantic_feline", "relationship": "isA"},
      {"from": "semantic_feline", "to": "semantic_animal", "relationship": "isA"},

      {"from": "verb_tinu", "to": "tense_pres_3sg_f_n", "relationship": "conjugatesWith", "form": "తింటుంది"},
      {"from": "verb_tinu", "to": "dep_obj", "relationship": "assignsRole", "thetaRole": "theta_theme"},
      {"from": "syntax_sov", "to": "verb_tinu", "relationship": "hasExampleComponent", "role": "verb"},

      // === ADVANCED SEMANTIC EDGES ===
      {"from": "verb_tinu", "to": "frame_ingestion", "relationship": "evokes"},
      {"from": "verb_tinu", "to": "fe_ingestor", "relationship": "assignsRole", "mapping": "subject"},
      {"from": "verb_tinu", "to": "fe_ingestible", "relationship": "assignsRole", "mapping": "object"},
      {"from": "noun_pilli", "to": "fe_ingestor", "relationship": "canFill", "selectionalRestriction": "animate"},

      // === FORMAL INFERENCE EDGES ===
      {"from": "rule_eat_implies_animal", "to": "verb_tinu", "relationship": "appliesTo", "condition": "default"},
      {"from": "rule_eat_implies_animal", "to": "semantic_animal", "relationship": "infers", "confidence": 0.95},
      {"from": "rule_causal_chain_hunger", "to": "rule_eat_implies_animal", "relationship": "precedes", "temporalOrder": "before"},

      // === NEURAL-SYMBOLIC INTEGRATION EDGES ===
      {"from": "neural_module_bert", "to": "noun_pilli", "relationship": "neurallyLinked", "embeddingSpace": "vector_space_768d"},
      {"from": "neural_module_bert", "to": "verb_tinu", "relationship": "neurallyLinked", "embeddingSpace": "vector_space_768d"},
      {"from": "symbolic_reasoner", "to": "neural_module_bert", "relationship": "integratesWith", "integrationType": "neurosymbolic_fusion"},

      // === ONTOLOGICAL REASONING EDGES ===
      {"from": "ontology_agriculture", "to": "noun_pilli", "relationship": "validates", "context": "పంట కాదు", "logicalStatement": "Crop ⊓ Animal ⊑ ⊥"},
      {"from": "ontology_agriculture", "to": "prag_particle_kada", "relationship": "triggers", "response": "అవును, సరిగానే చెప్పారు", "certainty": 0.9},

      // === CROSS-LINGUAL EDGES ===
      {"from": "noun_pilli", "to": "crosslingual_dravidian", "relationship": "crossLingualMatch", "language": "tamil", "word": "பூனை"},
      {"from": "verb_tinu", "to": "crosslingual_dravidian", "relationship": "crossLingualMatch", "language": "kannada", "word": "ತಿನ್ನು"},

      // === COGNITIVE AND MULTI-MODAL EDGES ===
      {"from": "cognitive_script_dining", "to": "verb_tinu", "relationship": "contains", "step": "consume_food"},
      {"from": "multimodal_cat", "to": "noun_pilli", "relationship": "multimodalGrounds", "modality": "visual", "strength": 0.94},
      {"from": "multimodal_cat", "to": "noun_pilli", "relationship": "multimodalGrounds", "modality": "auditory", "strength": 0.87},

      // === TINYAI OPTIMIZATION EDGES ===
      {"from": "tinyai_profile_100mb", "to": "logic_module_reasoning", "relationship": "optimizedFor", "optimizationLevel": "high"},
      {"from": "tinyai_profile_100mb", "to": "neural_module_bert", "relationship": "uses", "version": "distilled"},
      {"from": "logic_module_reasoning", "to": "ontology_agriculture", "relationship": "uses", "reasoningType": "domain_specific"}
    ],

    "validation": {
      "jsonSchema": {
        "$schema": "http://json-schema.org/draft-07/schema#",
        "title": "KG-Telugu v4.5",
        "type": "object",
        "required": ["metadata", "graph"],
        "properties": {
          "metadata": {"type": "object"},
          "graph": {
            "type": "object",
            "required": ["nodes", "edges"],
            "properties": {
              "nodes": {"type": "array", "items": {"type": "object", "required": ["id", "type"]}},
              "edges": {"type": "array", "items": {"type": "object", "required": ["from", "to", "relationship"]}}
            }
          }
        }
      },
      "logicConsistency": {
        "descriptionLogic": "SHOIN(D)",
        "consistencyChecker": "HermiT",
        "constraints": ["no_cyclic_inheritance", "domain_range_compatibility"]
      },
      "crossModalConsistency": {
        "checkers": ["visual_text_alignment", "auditory_text_alignment"],
        "threshold": 0.85
      }
    },

    "nlu_generation": {
      "analyzer": {
        "steps": [
          "tokenize_graph_graphemes",
          "morph_analyze (rules + lexicon)",
          "apply_morphophonemics",
          "map_UD",
          "build_dependency_tree",
          "semantic_role_labeling",
          "frame_semantic_parsing",
          "neural_contextual_disambiguation",
          "apply_inference_rules",
          "contextual_pragmatics",
          "cross_modal_integration"
        ],
        "neuralComponents": ["bert_contextualizer", "transformer_parser"],
        "symbolicComponents": ["rule_applier", "ontology_reasoner"]
      },
      "generator": {
        "inputs": ["logical_form", "semantic_frame", "pragmatic_context", "multimodal_context"],
        "procedure": [
          "select_paradigm",
          "attach_morphemes",
          "apply_allomorphy",
          "apply_phonological_rules",
          "apply_honorifics",
          "neural_surface_realization",
          "generate_response_with_reasoning"
        ],
        "neuralComponents": ["transformer_generator", "style_transfer"],
        "symbolicComponents": ["morphological_generator", "syntax_realizer"]
      }
    },

    "reasoning_capabilities": {
      "deductive": ["modus_ponens", "modus_tollens", "syllogism"],
      "inductive": ["generalization", "analogy", "statistical_learning"],
      "abductive": ["explanation_generation", "hypothesis_formation"],
      "temporal": ["event_ordering", "narrative_understanding"],
      "causal": ["cause_effect", "intervention_prediction"],
      "counterfactual": ["what_if_scenarios", "alternative_outcomes"]
    }
  }
}
